<?xml version="1.0" encoding="UTF-8"?>
<settings>
  <schemaSystemId>file:/Users/taraathan/Repositories/RuleML/Github/reaction-ruleml/auto-gen/dr-rnc/simp-dr-autogen-normal.rnc.xsd</schemaSystemId>
  <documentRoot>Query</documentRoot>
  <outputFolder>/Users/taraathan/Repositories/RuleML/Github/reaction-ruleml/auto-gen/dr-rnc</outputFolder>
  <filenamePrefix>instance-rnc-query</filenamePrefix>
  <filenameExtension>xml</filenameExtension>
  <noOfInstances>1</noOfInstances>
  <openFirstInstance>true</openFirstInstance>
  <defaultNamespace>http://ruleml.org/spec</defaultNamespace>
  <valuesMaxLength>30</valuesMaxLength>
  <isUseIncrementalNamesForValues>true</isUseIncrementalNamesForValues>
  <discardOptionalElementsAfterNestedLevel>2</discardOptionalElementsAfterNestedLevel>
  <namespaceMapping ns="http://ruleml.org/spec" proxy="ruleml"/>
  <element namespace="&lt;ANY>" name="&lt;ANY>">
    <generateOptionalElements>true</generateOptionalElements>
    <generateOptionalAttributes>true</generateOptionalAttributes>
    <valuesForContentType>RANDOM</valuesForContentType>
    <preferredNumberOfRepetitions>1</preferredNumberOfRepetitions>
    <maximumRecursivityLevel>9</maximumRecursivityLevel>
    <alternativeStrategy>RANDOM</alternativeStrategy>
    <choicesAndSubstitutions strategy="RANDOM" generateOthersAsComments="false"/>
    <attribute namespace="&lt;ANY>" name="&lt;ANY>">
    </attribute>
  </element>
</settings>